django_auth_exchange/VERSION_STAMP
django_auth_exchange/__init__.py
django_auth_exchange/apps.py
django_auth_exchange/backends.py
django_auth_exchange/settings.py
django_auth_exchange/urls.py
django_auth_exchange/version.py
django_auth_exchange/wsgi.py
django_auth_exchange-0.1.2.dist-info/LICENSE
django_auth_exchange-0.1.2.dist-info/METADATA
django_auth_exchange-0.1.2.dist-info/WHEEL
django_auth_exchange-0.1.2.dist-info/top_level.txt
django_auth_exchange-0.1.2.dist-info/RECORD
